dftimewolf/__init__.py
dftimewolf/config.py
dftimewolf/cli/__init__.py
dftimewolf/cli/dftimewolf_recipes.py
dftimewolf/lib/__init__.py
dftimewolf/lib/errors.py
dftimewolf/lib/module.py
dftimewolf/lib/resources.py
dftimewolf/lib/state.py
dftimewolf/lib/timesketch_utils.py
dftimewolf/lib/utils.py
dftimewolf/lib/collectors/__init__.py
dftimewolf/lib/collectors/audit_log_pb2.py
dftimewolf/lib/collectors/filesystem.py
dftimewolf/lib/collectors/gcloud.py
dftimewolf/lib/collectors/gcp_logging.py
dftimewolf/lib/collectors/grr_base.py
dftimewolf/lib/collectors/grr_hosts.py
dftimewolf/lib/collectors/grr_hunt.py
dftimewolf/lib/containers/__init__.py
dftimewolf/lib/containers/containers.py
dftimewolf/lib/containers/interface.py
dftimewolf/lib/exporters/__init__.py
dftimewolf/lib/exporters/gce_disk_export.py
dftimewolf/lib/exporters/local_filesystem.py
dftimewolf/lib/exporters/scp_ex.py
dftimewolf/lib/exporters/timesketch.py
dftimewolf/lib/modules/__init__.py
dftimewolf/lib/modules/manager.py
dftimewolf/lib/preflights/__init__.py
dftimewolf/lib/processors/__init__.py
dftimewolf/lib/processors/gcp_logging_timesketch.py
dftimewolf/lib/processors/grepper.py
dftimewolf/lib/processors/localplaso.py
dftimewolf/lib/processors/turbinia.py
dftimewolf/lib/recipes/__init__.py
dftimewolf/lib/recipes/manager.py
dftimewolf-20200608a0.data/data/share/dftimewolf/config.json
dftimewolf-20200608a0.data/data/share/dftimewolf/recipes/gce_disk_export.json
dftimewolf-20200608a0.data/data/share/dftimewolf/recipes/gcp_forensics.json
dftimewolf-20200608a0.data/data/share/dftimewolf/recipes/gcp_logging_cloudaudit_ts.json
dftimewolf-20200608a0.data/data/share/dftimewolf/recipes/gcp_logging_collect.json
dftimewolf-20200608a0.data/data/share/dftimewolf/recipes/gcp_logging_gce_instance_ts.json
dftimewolf-20200608a0.data/data/share/dftimewolf/recipes/gcp_logging_gce_ts.json
dftimewolf-20200608a0.data/data/share/dftimewolf/recipes/gcp_turbinia_disk_copy_ts.json
dftimewolf-20200608a0.dist-info/AUTHORS
dftimewolf-20200608a0.dist-info/LICENSE
dftimewolf-20200608a0.dist-info/METADATA
dftimewolf-20200608a0.dist-info/WHEEL
dftimewolf-20200608a0.dist-info/entry_points.txt
dftimewolf-20200608a0.dist-info/top_level.txt
dftimewolf-20200608a0.dist-info/RECORD
