Metadata-Version: 2.1
Name: dftimewolf
Version: 20200608a0
Summary: Digital forensic orchestration.
Home-page: https://github.com/log2timeline/dftimewolf
Maintainer: Log2Timeline maintainers
Maintainer-email: log2timeline-maintainers@googlegroups.com
License: Apache License, Version 2.0
Platform: UNKNOWN
Classifier: Development Status :: 4 - Beta
Classifier: Environment :: Console
Classifier: Operating System :: OS Independent
Classifier: Programming Language :: Python
Requires-Dist: altair (==4.1.0)
Requires-Dist: attrs (==19.3.0)
Requires-Dist: backcall (==0.1.0)
Requires-Dist: beautifulsoup4 (==4.9.1)
Requires-Dist: boto3 (==1.13.24)
Requires-Dist: botocore (==1.16.24)
Requires-Dist: cachetools (==4.1.0)
Requires-Dist: certifi (==2020.4.5.2)
Requires-Dist: cffi (==1.14.0)
Requires-Dist: chardet (==3.0.4)
Requires-Dist: click (==7.1.2)
Requires-Dist: colorlog (==2.10.0)
Requires-Dist: cryptography (==2.8)
Requires-Dist: decorator (==4.4.2)
Requires-Dist: docutils (==0.15.2)
Requires-Dist: entrypoints (==0.3)
Requires-Dist: filelock (==3.0.12)
Requires-Dist: future (==0.17.1)
Requires-Dist: google-api-core[grpc] (==1.19.1)
Requires-Dist: google-api-python-client (==1.9.1)
Requires-Dist: google-auth-httplib2 (==0.0.3)
Requires-Dist: google-auth-oauthlib (==0.4.1)
Requires-Dist: google-auth (==1.16.1)
Requires-Dist: google-cloud-core (==1.3.0)
Requires-Dist: google-cloud-datastore (==1.12.0)
Requires-Dist: google-cloud-logging (==1.15.0)
Requires-Dist: google-cloud-pubsub (==1.4.2)
Requires-Dist: google-cloud-storage (==1.28.1)
Requires-Dist: google-resumable-media (==0.5.1)
Requires-Dist: googleapis-common-protos[grpc] (==1.52.0)
Requires-Dist: grpc-google-iam-v1 (==0.12.3)
Requires-Dist: grpcio (==1.29.0)
Requires-Dist: grr-api-client (==3.4.0.post1)
Requires-Dist: grr-response-proto (==3.4.0.post1)
Requires-Dist: httplib2 (==0.18.1)
Requires-Dist: idna (==2.8)
Requires-Dist: ipython-genutils (==0.2.0)
Requires-Dist: ipython (==7.2.0)
Requires-Dist: jedi (==0.17.0)
Requires-Dist: jinja2 (==2.11.2)
Requires-Dist: jmespath (==0.10.0)
Requires-Dist: jsonschema (==3.2.0)
Requires-Dist: libcloudforensics (==20200520)
Requires-Dist: markupsafe (==1.1.1)
Requires-Dist: numpy (==1.18.5)
Requires-Dist: oauth2client (==4.1.3)
Requires-Dist: oauthlib (==3.1.0)
Requires-Dist: pandas (==1.0.4)
Requires-Dist: parso (==0.7.0)
Requires-Dist: pickleshare (==0.7.5)
Requires-Dist: prompt-toolkit (==2.0.10)
Requires-Dist: protobuf (==3.11.1)
Requires-Dist: psq (==0.8.0)
Requires-Dist: ptyprocess (==0.6.0)
Requires-Dist: pyasn1-modules (==0.2.8)
Requires-Dist: pyasn1 (==0.4.8)
Requires-Dist: pycparser (==2.20)
Requires-Dist: pygments (==2.6.1)
Requires-Dist: pyopenssl (==19.1.0)
Requires-Dist: pypdf2 (==1.26.0)
Requires-Dist: pyrsistent (==0.16.0)
Requires-Dist: python-dateutil (==2.8.1)
Requires-Dist: pytz (==2020.1)
Requires-Dist: pyyaml (==5.3.1)
Requires-Dist: requests-oauthlib (==1.3.0)
Requires-Dist: requests (==2.22.0)
Requires-Dist: rsa (==4.0)
Requires-Dist: s3transfer (==0.3.3)
Requires-Dist: six (==1.15.0)
Requires-Dist: soupsieve (==2.0.1)
Requires-Dist: timesketch-api-client (==20200602)
Requires-Dist: timesketch-import-client (==20200527)
Requires-Dist: toolz (==0.10.0)
Requires-Dist: traitlets (==4.3.3)
Requires-Dist: turbinia (==20190819.9)
Requires-Dist: uritemplate (==3.0.1)
Requires-Dist: wcwidth (==0.2.4)
Requires-Dist: werkzeug (==0.16.0)
Requires-Dist: xlrd (==1.2.0)
Requires-Dist: zipp (==3.1.0)
Requires-Dist: urllib3[secure] (==1.25.9) ; python_version != "3.4"
Requires-Dist: importlib-metadata (==1.6.1) ; python_version < "3.8"
Requires-Dist: pexpect (==4.8.0) ; sys_platform != "win32"
Requires-Dist: appnope (==0.1.0) ; sys_platform == "darwin"
